<?xml version="1.0" encoding="UTF-8" standalone="yes" ?>
<FileZilla3>
    <Layout Builddate="2014-10-16" Buildtime="11:20:13">
        <Resources>
            <xrc file="certificate.xrc" date="1413451315" />
            <xrc file="dialogs.xrc" date="1413451315" />
            <xrc file="inputdialog.xrc" date="1413451315" />
            <xrc file="menus.xrc" date="1413451315" />
            <xrc file="netconfwizard.xrc" date="1413451315" />
            <xrc file="quickconnectbar.xrc" date="1413451315" />
            <xrc file="settings.xrc" date="1413451315" />
            <xrc file="sitemanager.xrc" date="1413451315" />
            <xrc file="toolbar.xrc" date="1413451315" />
            <xrc file="update.xrc" date="1413451315" />
        </Resources>
        <Language id="default" date="">
            <Font font="0;13;70;90;90;0;.Helvetica Neue DeskInterface;49" width="787" height="15" />
            <Dialog name="Site Manager" width="650" />
        </Language>
    </Layout>
</FileZilla3>
